{
    "Actor": {},
    "Item": {
        "types": [
            "arma",
            "equipamento",
            "ferramenta",
            "caminho",
            "consumivel",
            "habilidade",
            "tesouro"
        ],
        "templates": {
            "descricaoDeItem": {
                "descricao": ""
            }
         
        },
        "arma": {
            "templates": [
                "descricaoDeItem"
            ],
            "rolls": [],
            "criticoM": 20,
            "criticoX": 2,
            "alcance": "",
            "tipoUso": "simples",
            "propriedades": {}
        }
    }
}